{
    "en": {
        "navbar_home": "Home",
        "navbar_news": "News",
        "navbar_donate": "Donation",
        "navbar_about_server": "About Server",
        "navbar_login": "Login",
        "language": "Language",
        "logout": "Logout",
        "about_server_title": "ABOUT SERVER",
        "rates_title": "RATES",
        "enchant_settings_title": "ENCHANT SETTINGS",
        "enchant_success_rates_title": "ENCHANT SUCCESS RATES",
        "rate_xp": "RATE XP",
        "rate_sp": "RATE SP",
        "rate_drop_adena": "RATE DROP ADENA",
        "safe_enchant": "SAFE ENCHANT",
        "max_weapon_enchant": "MAX WEAPON ENCHANT",
        "max_armor_enchant": "MAX ARMOR ENCHANT",
        "max_jewel_enchant": "MAX JEWEL ENCHANT",
        "normal_scroll": "NORMAL SCROLL",
        "blessed_scroll": "BLESSED SCROLL",
        "crystal_scroll": "CRYSTAL SCROLL"
    },
    "ka": {
        "navbar_home": "მთავარი",
        "navbar_news": "სიახლეები",
        "navbar_donate": "დონაცია",
        "navbar_about_server": "სერვერის შესახებ",
        "navbar_login": "შესვლა",
        "about_server_title": "სერვერის შესახებ",
        "rates_title": "გაკვეთილები",
        "enchant_settings_title": "ენჩანთის პარამეტრები",
        "enchant_success_rates_title": "ენჩანთის წარმატების მაჩვენებლები",
        "rate_xp": "XP სიჩქარე",
        "language": "ენა",
        "rate_sp": "SP სიჩქარე",
        "logout": "გასვლა",
        "rate_drop_adena": "Adena შესვენების სიჩქარე",
        "safe_enchant": "უსაფრთხო ენჩანთი",
        "max_weapon_enchant": "მაქს. იარაღის ენჩანთი",
        "max_armor_enchant": "მაქს. აჯანყების ენჩანთი",
        "max_jewel_enchant": "მაქს. სამკაულების ენჩანთი",
        "normal_scroll": "ნორმალური სკროლი",
        "blessed_scroll": "მორწმუნე სკროლი",
        "crystal_scroll": "კრისტალური სკროლი"
    },
    "ru": {
        "navbar_home": "Главная",
        "navbar_news": "Новости",
        "navbar_donate": "Пожертвования",
        "navbar_about_server": "О сервере",
        "navbar_login": "Вход",
        "about_server_title": "О сервере",
        "rates_title": "Тарифы",
        "enchant_settings_title": "Настройки зачарования",
        "enchant_success_rates_title": "Уровни успеха зачарования",
        "rate_xp": "Тариф XP",
        "rate_sp": "Тариф SP",
        "language": "Язык",
        "logout": "Выйти",
        "rate_drop_adena": "Тариф выпадения Adena",
        "safe_enchant": "Безопасное зачарование",
        "max_weapon_enchant": "Макс. зачарование оружия",
        "max_armor_enchant": "Макс. зачарование брони",
        "max_jewel_enchant": "Макс. зачарование украшений",
        "normal_scroll": "Обычный свиток",
        "blessed_scroll": "Благословенный свиток",
        "crystal_scroll": "Кристальный свиток"
    }
}